cmd_gpt_utils/__init__.py
cmd_gpt_utils/__main__.py
cmd_gpt_utils/api.py
cmd_gpt_utils/app.py
cmd_gpt_utils/cli.py
cmd_gpt_utils/config.py
cmd_gpt_utils/exceptions.py
cmd_gpt_utils/models.py
cmd_gpt_utils/processing.py
cmd_gpt_utils-0.1.0.dist-info/METADATA
cmd_gpt_utils-0.1.0.dist-info/WHEEL
cmd_gpt_utils-0.1.0.dist-info/entry_points.txt
cmd_gpt_utils-0.1.0.dist-info/licenses/LICENSE
cmd_gpt_utils-0.1.0.dist-info/RECORD
