Metadata-Version: 2.4
Name: cmd_gpt_utils
Version: 0.1.0
Summary: A command-line tool to interact with GPT APIs.
Author-email: LinearKF <creeper_lkf@qq.com>
License-File: LICENSE
Classifier: License :: OSI Approved :: MIT License
Classifier: Operating System :: OS Independent
Classifier: Programming Language :: Python :: 3
Requires-Python: >=3.8
Requires-Dist: argcomplete
Requires-Dist: python-dotenv
Requires-Dist: pyyaml
Requires-Dist: requests
Requires-Dist: sseclient-py
Provides-Extra: test
Requires-Dist: fastapi; extra == 'test'
Requires-Dist: pytest; extra == 'test'
Requires-Dist: pytest-cov; extra == 'test'
Requires-Dist: requests; extra == 'test'
Requires-Dist: uvicorn[standard]; extra == 'test'
